uv2conda/__init__.py
uv2conda/__main__.py
uv2conda/conda.py
uv2conda/console.py
uv2conda/main.py
uv2conda/pip.py
uv2conda/py.typed
uv2conda/python.py
uv2conda/uv.py
uv2conda-1.0.1.dist-info/METADATA
uv2conda-1.0.1.dist-info/WHEEL
uv2conda-1.0.1.dist-info/entry_points.txt
uv2conda-1.0.1.dist-info/RECORD
