Metadata-Version: 2.4
Name: uv2conda
Version: 1.0.1
Summary: Create a Conda environment file from a Python project using uv.
Project-URL: Homepage, https://github.com/fepegar/uv2conda
Project-URL: Source, https://github.com/fepegar/uv2conda
Author-email: Fernando Pérez-García <fepegar@gmail.com>
Requires-Python: >=3.9
Requires-Dist: loguru
Requires-Dist: packaging
Requires-Dist: pyyaml
Requires-Dist: typer
